pyjssocket/__init__.py
pyjssocket-1.0.5.dist-info/licenses/LICENCE
pyjssocket-1.0.5.dist-info/METADATA
pyjssocket-1.0.5.dist-info/WHEEL
pyjssocket-1.0.5.dist-info/top_level.txt
pyjssocket-1.0.5.dist-info/RECORD
