Metadata-Version: 2.4
Name: pyjssocket
Version: 1.0.5
Summary: A Python library that lets you communicate through JavaScript WebSocket client
Author-email: Dmytro Terekhov <terekhov160997@gmail.com>
License-Expression: MIT
Project-URL: Homepage, https://github.com/dododo25/pyjssocket
Project-URL: Issues, https://github.com/dododo25/pyjssocket/issues
Classifier: Programming Language :: Python :: 3
Classifier: Operating System :: OS Independent
Requires-Python: >=3.9
License-File: LICENCE
Dynamic: license-file
